README_zh.md
aslooper.py
aslooper-1.3.0.dist-info/LICENSE
aslooper-1.3.0.dist-info/METADATA
aslooper-1.3.0.dist-info/WHEEL
aslooper-1.3.0.dist-info/RECORD
