Metadata-Version: 2.1
Name: aslooper
Version: 1.3.0
Summary: looper-佛跳墙活套：捕获asyncio cancel报错。
Home-page: https://vastxiao.github.io/
License: MIT
Keywords: async,asyncio,loop
Author: vastxiao
Author-email: vastxiao@gmail.com
Requires-Python: >=3.11
Classifier: License :: OSI Approved :: MIT License
Classifier: Programming Language :: Python :: 3
Classifier: Programming Language :: Python :: 3.11
Classifier: Programming Language :: Python :: 3.12
